tubescience_cli/__init__.py
tubescience_cli/__main__.py
tubescience_cli/config.py
tubescience_cli/hashing.py
tubescience_cli/main.py
tubescience_cli/retool_rpc.py
tubescience_cli/models/__init__.py
tubescience_cli/models/classification.py
tubescience_cli/resources/__init__.py
tubescience_cli/resources/airbyte.py
tubescience_cli/resources/asset_manager.py
tubescience_cli/resources/brightdata.py
tubescience_cli/resources/mixpeek.py
tubescience_cli/resources/retool.py
tubescience_cli/resources/simba.py
tubescience_cli/resources/snowflake.py
tubescience_cli/resources/temporal.py
tubescience_cli/resources/vellum.py
tubescience_cli/temporal/__init__.py
tubescience_cli/temporal/pydantic_converter.py
tubescience_cli-0.0.10.dist-info/METADATA
tubescience_cli-0.0.10.dist-info/WHEEL
tubescience_cli-0.0.10.dist-info/entry_points.txt
tubescience_cli-0.0.10.dist-info/licenses/LICENSE
tubescience_cli-0.0.10.dist-info/RECORD
