Metadata-Version: 2.4
Name: tubescience-cli
Version: 0.0.10
Summary: TubeScience CLI tools
Project-URL: Homepage, https://jmosbacher.github.io/tubescience-cli/
Project-URL: Repository, https://github.com/jmosbacher/tubescience-cli
Project-URL: Documentation, https://jmosbacher.github.io/tubescience-cli/
Author-email: Yossi Mosbacher <yossi.mosbacher@tubescience.com>
License-File: LICENSE
Keywords: python
Classifier: Intended Audience :: Developers
Classifier: Programming Language :: Python
Classifier: Programming Language :: Python :: 3
Classifier: Programming Language :: Python :: 3.9
Classifier: Programming Language :: Python :: 3.10
Classifier: Programming Language :: Python :: 3.11
Classifier: Programming Language :: Python :: 3.12
Classifier: Programming Language :: Python :: 3.13
Classifier: Topic :: Software Development :: Libraries :: Python Modules
Requires-Python: <4.0,>=3.10
Requires-Dist: app-paths>=0.0.8
Requires-Dist: httpx>=0.25.2
Requires-Dist: pydantic-settings>=2.6.1
Requires-Dist: pydantic>=2.10.3
Requires-Dist: retoolrpc>=0.1.2
Requires-Dist: snowflake-connector-python>=3.12.4
Requires-Dist: temporalio>=1.8.0
Requires-Dist: typer>=0.14.0
Requires-Dist: vellum-ai>=0.11.0
